odoo9_addon_base_unece-9.0.1.0.0-py2.7-nspkg.pth
odoo_addons/base_unece/__openerp__.py
odoo_addons/base_unece/__init__.py
odoo_addons/base_unece/README.rst
odoo_addons/base_unece/security/ir.model.access.csv
odoo_addons/base_unece/models/unece_code_list.py
odoo_addons/base_unece/models/__init__.py
odoo_addons/base_unece/views/unece_code_list.xml
odoo9_addon_base_unece-9.0.1.0.0.dist-info/top_level.txt
odoo9_addon_base_unece-9.0.1.0.0.dist-info/WHEEL
odoo9_addon_base_unece-9.0.1.0.0.dist-info/RECORD
odoo9_addon_base_unece-9.0.1.0.0.dist-info/metadata.json
odoo9_addon_base_unece-9.0.1.0.0.dist-info/DESCRIPTION.rst
odoo9_addon_base_unece-9.0.1.0.0.dist-info/METADATA
odoo9_addon_base_unece-9.0.1.0.0.dist-info/namespace_packages.txt
